[
  {
    "Amount": 2513213.0,
    "AmountPaid": 0.0,
    "PaymentDate": "2025-05-22T17:12:30.4046005Z",
    "PaymentStatus": "Initiated",
    "OrderId": "122132",
    "OrderDescription": "1231132",
    "Email": "t@gmail.com",
    "PaymentId": null
  },
  {
    "Amount": 2513213.0,
    "AmountPaid": 0.0,
    "PaymentDate": "2025-05-22T17:12:45.0164403Z",
    "PaymentStatus": "Initiated",
    "OrderId": "122132",
    "OrderDescription": "1231132",
    "Email": "t@gmail.com",
    "PaymentId": null
  }
]